understory/term/__init__.py
understory/term/cli.py
understory_term-0.0.6.dist-info/LICENSE
understory_term-0.0.6.dist-info/WHEEL
understory_term-0.0.6.dist-info/METADATA
understory_term-0.0.6.dist-info/RECORD
