Metadata-Version: 2.1
Name: understory-term
Version: 0.0.6
Summary: Tools for metamodern terminal development
License: AGPL-3.0-or-later
Author: Angelo Gladding
Author-email: angelo@lahacker.net
Requires-Python: >=3.7,<4.0
Classifier: License :: OSI Approved :: GNU Affero General Public License v3 or later (AGPLv3+)
Classifier: Programming Language :: Python :: 3
Classifier: Programming Language :: Python :: 3.7
Classifier: Programming Language :: Python :: 3.8
Classifier: Programming Language :: Python :: 3.9
Requires-Dist: argcomplete (>=1.12.3,<2.0.0)
Project-URL: Homepage, https://github.com/canopy/understory-term
